pyreds/__init__.py
pyreds/phonetics.py
pyreds/reds.py
pyreds-0.1.4.dist-info/LICENSE
pyreds-0.1.4.dist-info/METADATA
pyreds-0.1.4.dist-info/WHEEL
pyreds-0.1.4.dist-info/top_level.txt
pyreds-0.1.4.dist-info/RECORD
