Metadata-Version: 2.1
Name: pyreds
Version: 0.1.4
Summary: Simple full text search module for Python, backed by Redis
Home-page: https://github.com/7anshuai/pyreds
Author: Tan Shuai
Author-email: 7anshuai@gmail.com
License: MIT
Download-URL: https://github.com/7anshuai/pyreds/archive/0.1.3.tar.gz
Keywords: redis,full text search
Platform: UNKNOWN
Classifier: Intended Audience :: Developers
Classifier: Operating System :: OS Independent
Classifier: Natural Language :: English
Classifier: Programming Language :: Python
Classifier: Programming Language :: Python :: 2
Classifier: Programming Language :: Python :: 2.7
Classifier: Programming Language :: Python :: 3
Classifier: Programming Language :: Python :: 3.5
Classifier: Programming Language :: Python :: 3.6
Classifier: Topic :: Software Development :: Libraries :: Python Modules
Classifier: License :: OSI Approved :: MIT License
Requires-Dist: nltk (==3.4.5)
Requires-Dist: redis (==2.10.6)
